<?xml version="1.0" encoding="UTF-8"?>
<!-- IBM Confidential OCO Source Materials --><!-- (C) COPYRIGHT IBM CORP. 2011-2026 --><!-- The source code for this program is not published or otherwise divested of its trade secrets, irrespective of what has been deposited with the U.S. Copyright Office. --><Workflow><Header Type="4" WfStatus="10" IgnoreModuleLevel="0" InstanceData="0" LockRecord="0" Modifier="0"><ObjectLabelName><![CDATA[Root 0.0]]></ObjectLabelName><Name><![CDATA[triKeyWorkTask - Associate - Apply Template on Associate]]></Name><Module><![CDATA[triTask]]></Module><BO><![CDATA[triKeyWorkTask]]></BO><EventName><![CDATA[Associate]]></EventName><Description><![CDATA[Template Record Associate with Parent Record]]></Description><AssociationName><![CDATA[Associate Template]]></AssociationName><UpdatedBy><![CDATA[]]></UpdatedBy><AssociatedBO><![CDATA[triKeyWorkTask]]></AssociatedBO><AssociatedModule><![CDATA[triTask]]></AssociatedModule></Header><Tasks><Task Id="153778" Type="30" FilterOperator="10" RecurrenceId="0" MapId="-1" SRCTaskId="0" TRGTTaskId="0" AssigneeTaskId="0" SortCount="1" UseMap="1" LockUser="0" AssignToFlag="1" EstEndInDays="0" EstEndInHrs="0" EstEndInMins="0" DateContext="0" ServiceContext="1"><TaskLabel><![CDATA[Deasociate triWorkTask - Template from triWorkTask]]></TaskLabel><EventName><![CDATA[De-Associate]]></EventName><Description><![CDATA[]]></Description><DeleteSection><![CDATA[]]></DeleteSection><SumSection><![CDATA[]]></SumSection><SumField><![CDATA[]]></SumField><FilterSection><![CDATA[]]></FilterSection><FilterField><![CDATA[]]></FilterField><FilterValue><![CDATA[]]></FilterValue><ServiceAssociation><![CDATA[Associate Template]]></ServiceAssociation><TargetAssociation><![CDATA[]]></TargetAssociation><TransactionType><![CDATA[0]]></TransactionType><Status><![CDATA[0]]></Status><ParametersMapId><![CDATA[-1]]></ParametersMapId><FormulaRecalc><![CDATA[0]]></FormulaRecalc><Module><![CDATA[triTask]]></Module><BO><![CDATA[triKeyWorkTask]]></BO><AssignToUserMod><![CDATA[]]></AssignToUserMod><AssignToUserBO><![CDATA[]]></AssignToUserBO><AssignToUser><![CDATA[]]></AssignToUser><TaskRefs><TaskRef RefType="0" UseType="1" TaskRefType="0" CtxType="-1" RefTaskId="0"><RefSec><![CDATA[]]></RefSec><RefField><![CDATA[]]></RefField><RefAssoc><![CDATA[]]></RefAssoc><RefModule><![CDATA[triTask]]></RefModule><RefObject><![CDATA[triKeyWorkTask]]></RefObject><RefRecordMod><![CDATA[]]></RefRecordMod><RefRecordBO><![CDATA[]]></RefRecordBO><RefRecord><![CDATA[]]></RefRecord></TaskRef><TaskRef RefType="1" UseType="2" TaskRefType="3" CtxType="-1" RefTaskId="0"><RefSec><![CDATA[]]></RefSec><RefField><![CDATA[]]></RefField><RefAssoc><![CDATA[]]></RefAssoc><RefModule><![CDATA[triTask]]></RefModule><RefObject><![CDATA[triKeyWorkTask]]></RefObject></TaskRef></TaskRefs></Task><Task Id="151009" Type="9" FilterOperator="10" RecurrenceId="0" MapId="-1" SRCTaskId="-1" TRGTTaskId="-1" AssigneeTaskId="0" SortCount="1" UseMap="1" LockUser="0" AssignToFlag="1" EstEndInDays="0" EstEndInHrs="0" EstEndInMins="0" DateContext="0" ServiceContext="1"><TaskLabel><![CDATA[]]></TaskLabel><EventName><![CDATA[]]></EventName><Description><![CDATA[]]></Description><DeleteSection><![CDATA[]]></DeleteSection><SumSection><![CDATA[]]></SumSection><SumField><![CDATA[]]></SumField><FilterSection><![CDATA[]]></FilterSection><FilterField><![CDATA[]]></FilterField><FilterValue><![CDATA[]]></FilterValue><ServiceAssociation><![CDATA[]]></ServiceAssociation><TargetAssociation><![CDATA[]]></TargetAssociation><TransactionType><![CDATA[0]]></TransactionType><Status><![CDATA[0]]></Status><ParametersMapId><![CDATA[-1]]></ParametersMapId><FormulaRecalc><![CDATA[0]]></FormulaRecalc><Module><![CDATA[]]></Module><BO><![CDATA[]]></BO><AssignToUserMod><![CDATA[]]></AssignToUserMod><AssignToUserBO><![CDATA[]]></AssignToUserBO><AssignToUser><![CDATA[]]></AssignToUser><TaskRefs /></Task><Task Id="153765" Type="30" FilterOperator="10" RecurrenceId="0" MapId="-1" SRCTaskId="0" TRGTTaskId="0" AssigneeTaskId="0" SortCount="1" UseMap="1" LockUser="0" AssignToFlag="1" EstEndInDays="0" EstEndInHrs="0" EstEndInMins="0" DateContext="0" ServiceContext="1"><TaskLabel><![CDATA[Associate triKeyWorkTask - Template to triKeyWorkTask]]></TaskLabel><EventName><![CDATA[Associate]]></EventName><Description><![CDATA[Associate Template to Parent 
Using Temporary String]]></Description><DeleteSection><![CDATA[]]></DeleteSection><SumSection><![CDATA[]]></SumSection><SumField><![CDATA[]]></SumField><FilterSection><![CDATA[]]></FilterSection><FilterField><![CDATA[]]></FilterField><FilterValue><![CDATA[]]></FilterValue><ServiceAssociation><![CDATA[Temporary]]></ServiceAssociation><TargetAssociation><![CDATA[]]></TargetAssociation><TransactionType><![CDATA[0]]></TransactionType><Status><![CDATA[0]]></Status><ParametersMapId><![CDATA[-1]]></ParametersMapId><FormulaRecalc><![CDATA[0]]></FormulaRecalc><Module><![CDATA[triTask]]></Module><BO><![CDATA[triKeyWorkTask]]></BO><AssignToUserMod><![CDATA[]]></AssignToUserMod><AssignToUserBO><![CDATA[]]></AssignToUserBO><AssignToUser><![CDATA[]]></AssignToUser><TaskRefs><TaskRef RefType="0" UseType="1" TaskRefType="0" CtxType="-1" RefTaskId="0"><RefSec><![CDATA[]]></RefSec><RefField><![CDATA[]]></RefField><RefAssoc><![CDATA[]]></RefAssoc><RefModule><![CDATA[triTask]]></RefModule><RefObject><![CDATA[triKeyWorkTask]]></RefObject><RefRecordMod><![CDATA[]]></RefRecordMod><RefRecordBO><![CDATA[]]></RefRecordBO><RefRecord><![CDATA[]]></RefRecord></TaskRef><TaskRef RefType="1" UseType="2" TaskRefType="3" CtxType="-1" RefTaskId="0"><RefSec><![CDATA[]]></RefSec><RefField><![CDATA[]]></RefField><RefAssoc><![CDATA[]]></RefAssoc><RefModule><![CDATA[triTask]]></RefModule><RefObject><![CDATA[triKeyWorkTask]]></RefObject></TaskRef></TaskRefs></Task><Task Id="0" Type="1" FilterOperator="10" RecurrenceId="0" MapId="240666" SRCTaskId="-1" TRGTTaskId="-1" AssigneeTaskId="0" SortCount="1" UseMap="1" LockUser="0" AssignToFlag="1" EstEndInDays="0" EstEndInHrs="0" EstEndInMins="0" DateContext="0" ServiceContext="1"><TaskLabel><![CDATA[Start]]></TaskLabel><EventName><![CDATA[Associate]]></EventName><Description><![CDATA[]]></Description><DeleteSection><![CDATA[]]></DeleteSection><SumSection><![CDATA[]]></SumSection><SumField><![CDATA[]]></SumField><FilterSection><![CDATA[]]></FilterSection><FilterField><![CDATA[]]></FilterField><FilterValue><![CDATA[]]></FilterValue><ServiceAssociation><![CDATA[]]></ServiceAssociation><TargetAssociation><![CDATA[]]></TargetAssociation><TransactionType><![CDATA[0]]></TransactionType><Status><![CDATA[0]]></Status><ParametersMapId><![CDATA[-1]]></ParametersMapId><FormulaRecalc><![CDATA[0]]></FormulaRecalc><Module><![CDATA[triTask]]></Module><BO><![CDATA[triKeyWorkTask]]></BO><AssociatedModule><![CDATA[triTask]]></AssociatedModule><AssociatedBO><![CDATA[triKeyWorkTask]]></AssociatedBO><AssignToUserMod><![CDATA[]]></AssignToUserMod><AssignToUserBO><![CDATA[]]></AssignToUserBO><AssignToUser><![CDATA[]]></AssignToUser><TaskRefs /><Condition><Expression><![CDATA[ ]]></Expression></Condition></Task><Task Id="188146" Type="38" FilterOperator="10" RecurrenceId="0" MapId="-1" SRCTaskId="-1" TRGTTaskId="-1" AssigneeTaskId="0" SortCount="1" UseMap="1" LockUser="0" AssignToFlag="1" EstEndInDays="0" EstEndInHrs="0" EstEndInMins="0" DateContext="0" ServiceContext="1"><TaskLabel><![CDATA[Call triKeyWorkTask - Synchronous Map Template Data to Parent]]></TaskLabel><EventName><![CDATA[]]></EventName><Description><![CDATA[Call triKeyWorkTask - Synchronous Map Template Data to Parent]]></Description><DeleteSection><![CDATA[]]></DeleteSection><SumSection><![CDATA[]]></SumSection><SumField><![CDATA[]]></SumField><FilterSection><![CDATA[]]></FilterSection><FilterField><![CDATA[]]></FilterField><FilterValue><![CDATA[]]></FilterValue><ServiceAssociation><![CDATA[]]></ServiceAssociation><TargetAssociation><![CDATA[]]></TargetAssociation><TransactionType><![CDATA[0]]></TransactionType><Status><![CDATA[0]]></Status><ParametersMapId><![CDATA[-1]]></ParametersMapId><FormulaRecalc><![CDATA[0]]></FormulaRecalc><FilterClass><![CDATA[29]]></FilterClass><Module><![CDATA[triTask]]></Module><BO><![CDATA[triKeyWorkTask]]></BO><FilterBo><![CDATA[triKeyWorkTask - Synchronous - Map Template Data to Parent]]></FilterBo><FilterBoBO><![CDATA[triKeyWorkTask]]></FilterBoBO><FilterModule><![CDATA[triTask]]></FilterModule><AssignToUserMod><![CDATA[]]></AssignToUserMod><AssignToUserBO><![CDATA[]]></AssignToUserBO><AssignToUser><![CDATA[]]></AssignToUser><TaskRefs><TaskRef RefType="0" UseType="1" TaskRefType="0" CtxType="-1" RefTaskId="0"><RefSec><![CDATA[]]></RefSec><RefField><![CDATA[]]></RefField><RefAssoc><![CDATA[]]></RefAssoc><RefModule><![CDATA[triTask]]></RefModule><RefObject><![CDATA[triKeyWorkTask]]></RefObject><RefRecordMod><![CDATA[]]></RefRecordMod><RefRecordBO><![CDATA[]]></RefRecordBO><RefRecord><![CDATA[]]></RefRecord></TaskRef></TaskRefs></Task></Tasks><WFSteps><WFStep Id="0" Type="1" ParId="-1" /><WFStep Id="151009" Type="9" ParId="153778" /><WFStep Id="153765" Type="30" ParId="0" /><WFStep Id="153778" Type="30" ParId="188146" /><WFStep Id="188146" Type="38" ParId="153765" /></WFSteps></Workflow>
